yamlito/__init__.py
yamlito/config.py
yamlito/test/__init__.py
yamlito/test/test_config.py
yamlito-0.1.0.dist-info/LICENSE
yamlito-0.1.0.dist-info/METADATA
yamlito-0.1.0.dist-info/WHEEL
yamlito-0.1.0.dist-info/top_level.txt
yamlito-0.1.0.dist-info/RECORD
