Metadata-Version: 2.1
Name: yamlito
Version: 0.1.0
Summary: Simple yaml config loader
Home-page: https://github.com/hzanoli/yamlito
Author: Henrique Zanoli
Author-email: hzanoli@gmail.com
License: GNU Lesser General Public License v3.0
Platform: UNKNOWN
Requires-Dist: PyYAML
